contact/__init__.py
contact/forms.py
contact/locale/fr/LC_MESSAGES/django.mo
contact/locale/fr/LC_MESSAGES/django.po
contact/static/css/contact.css
contact/templates/contact/form.html
contact/templates/contact/thanks.html
contact/test_settings.py
contact/test_templates/base.html
contact/test_urls.py
contact/test_views.py
contact/urls.py
contact/views.py
myks_contact-1.6.dist-info/LICENSE
myks_contact-1.6.dist-info/WHEEL
myks_contact-1.6.dist-info/METADATA
myks_contact-1.6.dist-info/RECORD
