Metadata-Version: 2.1
Name: myks-contact
Version: 1.6
Summary: Simple contact form
Home-page: https://github.com/aaugustin/myks-contact
License: BSD-3-Clause
Author: Aymeric Augustin
Author-email: aymeric.augustin@m4x.org
Requires-Python: >=3.6,<4.0
Classifier: Development Status :: 5 - Production/Stable
Classifier: Environment :: Web Environment
Classifier: Framework :: Django
Classifier: Intended Audience :: Developers
Classifier: License :: OSI Approved :: BSD License
Classifier: Operating System :: OS Independent
Classifier: Programming Language :: Python :: 3
Classifier: Programming Language :: Python :: 3.10
Classifier: Programming Language :: Python :: 3.6
Classifier: Programming Language :: Python :: 3.7
Classifier: Programming Language :: Python :: 3.8
Classifier: Programming Language :: Python :: 3.9
Requires-Dist: django (>=2.2)
Project-URL: Repository, https://github.com/aaugustin/myks-contact
